<?xml version="1.0" encoding="utf-8"?>
<abapGit version="v1.0.0" serializer="LCL_OBJECT_VIEW" serializer_version="v1.0.0">
 <asx:abap xmlns:asx="http://www.sap.com/abapxml" version="1.0">
  <asx:values>
   <DD25V>
    <VIEWNAME>ZAGC_MRCONTACT</VIEWNAME>
    <AS4LOCAL>A</AS4LOCAL>
    <DDLANGUAGE>D</DDLANGUAGE>
    <AGGTYPE>V</AGGTYPE>
    <ROOTTAB>/IDXGC/MRCONTACT</ROOTTAB>
    <DDTEXT>Geschäftspartner für Ablesekarte</DDTEXT>
    <VIEWCLASS>C</VIEWCLASS>
    <CUSTOMAUTH>A</CUSTOMAUTH>
    <GLOBALFLAG>X</GLOBALFLAG>
   </DD25V>
   <DD26V_TABLE>
    <DD26V>
     <VIEWNAME>ZAGC_MRCONTACT</VIEWNAME>
     <TABNAME>/IDXGC/MRCONTACT</TABNAME>
     <TABPOS>0001</TABPOS>
     <FORTABNAME>/IDXGC/MRCONTACT</FORTABNAME>
    </DD26V>
   </DD26V_TABLE>
   <DD27P_TABLE>
    <DD27P>
     <VIEWFIELD>MANDT</VIEWFIELD>
     <TABNAME>/IDXGC/MRCONTACT</TABNAME>
     <FIELDNAME>MANDT</FIELDNAME>
     <KEYFLAG>X</KEYFLAG>
    </DD27P>
    <DD27P>
     <VIEWFIELD>ANLAGE</VIEWFIELD>
     <TABNAME>/IDXGC/MRCONTACT</TABNAME>
     <FIELDNAME>ANLAGE</FIELDNAME>
     <KEYFLAG>X</KEYFLAG>
     <SHLPORIGIN>D</SHLPORIGIN>
     <SHLPNAME>EANL</SHLPNAME>
     <SHLPFIELD>ANLAGE</SHLPFIELD>
     <LOGFLAG>X</LOGFLAG>
    </DD27P>
    <DD27P>
     <VIEWFIELD>FROMDATE</VIEWFIELD>
     <TABNAME>/IDXGC/MRCONTACT</TABNAME>
     <FIELDNAME>FROMDATE</FIELDNAME>
     <KEYFLAG>X</KEYFLAG>
     <SHLPORIGIN>T</SHLPORIGIN>
     <LOGFLAG>X</LOGFLAG>
    </DD27P>
    <DD27P>
     <VIEWFIELD>TODATE</VIEWFIELD>
     <TABNAME>/IDXGC/MRCONTACT</TABNAME>
     <FIELDNAME>TODATE</FIELDNAME>
     <SHLPORIGIN>T</SHLPORIGIN>
     <LOGFLAG>X</LOGFLAG>
    </DD27P>
    <DD27P>
     <VIEWFIELD>CONTACT_BP</VIEWFIELD>
     <TABNAME>/IDXGC/MRCONTACT</TABNAME>
     <FIELDNAME>CONTACT_BP</FIELDNAME>
     <SHLPORIGIN>D</SHLPORIGIN>
     <SHLPNAME>BUPA</SHLPNAME>
     <SHLPFIELD>PARTNER</SHLPFIELD>
    </DD27P>
    <DD27P>
     <VIEWFIELD>CR_NAME</VIEWFIELD>
     <TABNAME>/IDXGC/MRCONTACT</TABNAME>
     <FIELDNAME>CR_NAME</FIELDNAME>
    </DD27P>
    <DD27P>
     <VIEWFIELD>CR_DATE</VIEWFIELD>
     <TABNAME>/IDXGC/MRCONTACT</TABNAME>
     <FIELDNAME>CR_DATE</FIELDNAME>
     <SHLPORIGIN>T</SHLPORIGIN>
    </DD27P>
    <DD27P>
     <VIEWFIELD>CR_TIME</VIEWFIELD>
     <TABNAME>/IDXGC/MRCONTACT</TABNAME>
     <FIELDNAME>CR_TIME</FIELDNAME>
     <SHLPORIGIN>T</SHLPORIGIN>
    </DD27P>
    <DD27P>
     <VIEWFIELD>CH_NAME</VIEWFIELD>
     <TABNAME>/IDXGC/MRCONTACT</TABNAME>
     <FIELDNAME>CH_NAME</FIELDNAME>
    </DD27P>
    <DD27P>
     <VIEWFIELD>CH_DATE</VIEWFIELD>
     <TABNAME>/IDXGC/MRCONTACT</TABNAME>
     <FIELDNAME>CH_DATE</FIELDNAME>
     <SHLPORIGIN>T</SHLPORIGIN>
    </DD27P>
    <DD27P>
     <VIEWFIELD>CH_TIME</VIEWFIELD>
     <TABNAME>/IDXGC/MRCONTACT</TABNAME>
     <FIELDNAME>CH_TIME</FIELDNAME>
     <SHLPORIGIN>T</SHLPORIGIN>
     <LOGFLAG>X</LOGFLAG>
    </DD27P>
   </DD27P_TABLE>
  </asx:values>
 </asx:abap>
</abapGit>
