<?xml version="1.0" encoding="utf-8"?>
<abapGit version="v1.0.0" serializer="LCL_OBJECT_VIEW" serializer_version="v1.0.0">
 <asx:abap xmlns:asx="http://www.sap.com/abapxml" version="1.0">
  <asx:values>
   <DD25V>
    <VIEWNAME>/ADESSO/V_MDC_RI</VIEWNAME>
    <AS4LOCAL>A</AS4LOCAL>
    <DDLANGUAGE>D</DDLANGUAGE>
    <AGGTYPE>V</AGGTYPE>
    <ROOTTAB>/ADESSO/MDC_RAID</ROOTTAB>
    <DDTEXT>SDÄ: Customizing View zur Tabelle /ADESSO/MDC_RAID</DDTEXT>
    <VIEWCLASS>C</VIEWCLASS>
    <CUSTOMAUTH>C</CUSTOMAUTH>
    <GLOBALFLAG>X</GLOBALFLAG>
   </DD25V>
   <DD26V_TABLE>
    <DD26V>
     <VIEWNAME>/ADESSO/V_MDC_RI</VIEWNAME>
     <TABNAME>/ADESSO/MDC_RAID</TABNAME>
     <TABPOS>0001</TABPOS>
     <FORTABNAME>/ADESSO/MDC_RAID</FORTABNAME>
    </DD26V>
   </DD26V_TABLE>
   <DD27P_TABLE>
    <DD27P>
     <VIEWFIELD>EDIFACT_STRUCTUR</VIEWFIELD>
     <TABNAME>/ADESSO/MDC_RAID</TABNAME>
     <FIELDNAME>EDIFACT_STRUCTUR</FIELDNAME>
     <KEYFLAG>X</KEYFLAG>
    </DD27P>
    <DD27P>
     <VIEWFIELD>VALID_FROM</VIEWFIELD>
     <TABNAME>/ADESSO/MDC_RAID</TABNAME>
     <FIELDNAME>VALID_FROM</FIELDNAME>
     <KEYFLAG>X</KEYFLAG>
     <SHLPORIGIN>T</SHLPORIGIN>
    </DD27P>
    <DD27P>
     <VIEWFIELD>DISTRIBUTOR_ROLE</VIEWFIELD>
     <TABNAME>/ADESSO/MDC_RAID</TABNAME>
     <FIELDNAME>DISTRIBUTOR_ROLE</FIELDNAME>
     <SHLPORIGIN>F</SHLPORIGIN>
     <VALEXI>X</VALEXI>
    </DD27P>
    <DD27P>
     <VIEWFIELD>DISTRIBUTOR_AMID_SUPPLIER</VIEWFIELD>
     <TABNAME>/ADESSO/MDC_RAID</TABNAME>
     <FIELDNAME>DISTRIBUTOR_AMID_SUPPLIER</FIELDNAME>
    </DD27P>
    <DD27P>
     <VIEWFIELD>DISTRIBUTOR_AMID_MOS</VIEWFIELD>
     <TABNAME>/ADESSO/MDC_RAID</TABNAME>
     <FIELDNAME>DISTRIBUTOR_AMID_MOS</FIELDNAME>
    </DD27P>
    <DD27P>
     <VIEWFIELD>SUPPLIER_ROLE</VIEWFIELD>
     <TABNAME>/ADESSO/MDC_RAID</TABNAME>
     <FIELDNAME>SUPPLIER_ROLE</FIELDNAME>
     <SHLPORIGIN>F</SHLPORIGIN>
     <VALEXI>X</VALEXI>
    </DD27P>
    <DD27P>
     <VIEWFIELD>SUPPLIER_AMID</VIEWFIELD>
     <TABNAME>/ADESSO/MDC_RAID</TABNAME>
     <FIELDNAME>SUPPLIER_AMID</FIELDNAME>
    </DD27P>
    <DD27P>
     <VIEWFIELD>SUPPLIER_FUTURE_ROLE</VIEWFIELD>
     <TABNAME>/ADESSO/MDC_RAID</TABNAME>
     <FIELDNAME>SUPPLIER_FUTURE_ROLE</FIELDNAME>
     <SHLPORIGIN>F</SHLPORIGIN>
     <VALEXI>X</VALEXI>
    </DD27P>
    <DD27P>
     <VIEWFIELD>SUPPLIER_FUTURE_AMID</VIEWFIELD>
     <TABNAME>/ADESSO/MDC_RAID</TABNAME>
     <FIELDNAME>SUPPLIER_FUTURE_AMID</FIELDNAME>
    </DD27P>
    <DD27P>
     <VIEWFIELD>FEEDER_ROLE</VIEWFIELD>
     <TABNAME>/ADESSO/MDC_RAID</TABNAME>
     <FIELDNAME>FEEDER_ROLE</FIELDNAME>
     <SHLPORIGIN>F</SHLPORIGIN>
     <VALEXI>X</VALEXI>
    </DD27P>
    <DD27P>
     <VIEWFIELD>FEEDER_AMID</VIEWFIELD>
     <TABNAME>/ADESSO/MDC_RAID</TABNAME>
     <FIELDNAME>FEEDER_AMID</FIELDNAME>
    </DD27P>
    <DD27P>
     <VIEWFIELD>FEEDER_FUTURE_ROLE</VIEWFIELD>
     <TABNAME>/ADESSO/MDC_RAID</TABNAME>
     <FIELDNAME>FEEDER_FUTURE_ROLE</FIELDNAME>
     <SHLPORIGIN>F</SHLPORIGIN>
     <VALEXI>X</VALEXI>
    </DD27P>
    <DD27P>
     <VIEWFIELD>FEEDER_FUTURE_AMID</VIEWFIELD>
     <TABNAME>/ADESSO/MDC_RAID</TABNAME>
     <FIELDNAME>FEEDER_FUTURE_AMID</FIELDNAME>
    </DD27P>
    <DD27P>
     <VIEWFIELD>MOS_ROLE</VIEWFIELD>
     <TABNAME>/ADESSO/MDC_RAID</TABNAME>
     <FIELDNAME>MOS_ROLE</FIELDNAME>
     <SHLPORIGIN>F</SHLPORIGIN>
     <VALEXI>X</VALEXI>
    </DD27P>
    <DD27P>
     <VIEWFIELD>MOS_AMID</VIEWFIELD>
     <TABNAME>/ADESSO/MDC_RAID</TABNAME>
     <FIELDNAME>MOS_AMID</FIELDNAME>
    </DD27P>
    <DD27P>
     <VIEWFIELD>BMOS_ROLE</VIEWFIELD>
     <TABNAME>/ADESSO/MDC_RAID</TABNAME>
     <FIELDNAME>BMOS_ROLE</FIELDNAME>
     <SHLPORIGIN>F</SHLPORIGIN>
     <VALEXI>X</VALEXI>
    </DD27P>
    <DD27P>
     <VIEWFIELD>BMOS_AMID</VIEWFIELD>
     <TABNAME>/ADESSO/MDC_RAID</TABNAME>
     <FIELDNAME>BMOS_AMID</FIELDNAME>
    </DD27P>
   </DD27P_TABLE>
  </asx:values>
 </asx:abap>
</abapGit>
